pytest_alphamoon/__init__.py
pytest_alphamoon/_commons.py
pytest_alphamoon/adr_check.py
pytest_alphamoon/annotation_check.py
pytest_alphamoon/commit_message_check.py
pytest_alphamoon/import_check.py
pytest_alphamoon/init_check.py
pytest_alphamoon/newline_check.py
pytest_alphamoon/notebook_check.py
pytest_alphamoon/requirements_coherence_check.py
pytest_alphamoon/requirements_versions_check.py
pytest_alphamoon/sorted_requirements_check.py
pytest_alphamoon/testdir_check.py
pytest_alphamoon-2021.12.30.1308.dist-info/LICENSE
pytest_alphamoon-2021.12.30.1308.dist-info/METADATA
pytest_alphamoon-2021.12.30.1308.dist-info/WHEEL
pytest_alphamoon-2021.12.30.1308.dist-info/entry_points.txt
pytest_alphamoon-2021.12.30.1308.dist-info/top_level.txt
pytest_alphamoon-2021.12.30.1308.dist-info/RECORD
