Metadata-Version: 2.1
Name: pytest-alphamoon
Version: 2021.12.30.1308
Summary: Static code checks used at Alphamoon
Home-page: https://gitlab.com/alphamoon/internal_tools/pytest_alphamoon
Author: Jakub Binkowski
Author-email: jakub.binkowski@alphamoon.ai
Maintainer: Jakub Binkowski
Maintainer-email: dev@alphamoon.ai
License: MIT
Platform: UNKNOWN
Classifier: Development Status :: 5 - Production/Stable
Classifier: Framework :: Pytest
Classifier: Intended Audience :: Developers
Classifier: Topic :: Software Development :: Testing
Classifier: Programming Language :: Python
Classifier: Programming Language :: Python :: 3
Classifier: Programming Language :: Python :: 3.7
Classifier: Programming Language :: Python :: 3.8
Classifier: Programming Language :: Python :: Implementation :: PyPy
Classifier: Operating System :: OS Independent
Classifier: License :: OSI Approved :: MIT License
Requires-Python: >=3.7
License-File: LICENSE
Requires-Dist: git-python (>=1.0.3)
Requires-Dist: pytest (>=3.5.0)
